emergent/__init__.py
emergent/main.py
emergent-0.1.2.dist-info/METADATA
emergent-0.1.2.dist-info/WHEEL
emergent-0.1.2.dist-info/top_level.txt
emergent-0.1.2.dist-info/RECORD
